azubiheftApi/__init__.py
azubiheftApi/azubiheftApi.py
azubiheftApi/errors.py
tests/__init__.py
tests/test.py
azubiheftApi-1.0.0.dist-info/LICENSE
azubiheftApi-1.0.0.dist-info/METADATA
azubiheftApi-1.0.0.dist-info/WHEEL
azubiheftApi-1.0.0.dist-info/top_level.txt
azubiheftApi-1.0.0.dist-info/RECORD
