Metadata-Version: 2.1
Name: azubiheftApi
Version: 1.0.0
Summary: Azubiheft.de custom api
Home-page: https://github.com/leonkohli/azubiheft-api
Author: Leon Kohlhaussen
Author-email: kohli.leon@gmail.com
Classifier: License :: OSI Approved :: Apache Software License
Classifier: Programming Language :: Python :: 3
Classifier: Operating System :: OS Independent
Requires-Python: >=3.6
License-File: LICENSE
Requires-Dist: datetime
Requires-Dist: bs4
Requires-Dist: beautifulsoup4
Requires-Dist: requests
